janus_cloud-1.0.0.data/data/opt/janus-cloud/certs/mycert.key
janus_cloud-1.0.0.data/data/opt/janus-cloud/certs/mycert.pem
janus_cloud-1.0.0.data/data/opt/janus-cloud/conf/janus-proxy.plugin.p2pcall.yml
janus_cloud-1.0.0.data/data/opt/janus-cloud/conf/janus-proxy.plugin.videocall.yml
janus_cloud-1.0.0.data/data/opt/janus-cloud/conf/janus-proxy.plugin.videoroom.yml
janus_cloud-1.0.0.data/data/opt/janus-cloud/conf/janus-proxy.yml
janus_cloud-1.0.0.data/data/opt/janus-cloud/conf/janus-sentinel.yml
janus_cloud-1.0.0.data/data/opt/janus-cloud/html/p2pcalltest.html
janus_cloud-1.0.0.data/data/opt/janus-cloud/html/p2pcalltest.js
januscloud/__init__.py
januscloud/certs/mycert.key
januscloud/certs/mycert.pem
januscloud/common/__init__.py
januscloud/common/confparser.py
januscloud/common/error.py
januscloud/common/gsqlite3.py
januscloud/common/logger.py
januscloud/common/schema.py
januscloud/common/utils.py
januscloud/common/sdp_transform/__init__.py
januscloud/common/sdp_transform/__version__.py
januscloud/common/sdp_transform/grammar.py
januscloud/common/sdp_transform/parser.py
januscloud/common/sdp_transform/writer.py
januscloud/core/__init__.py
januscloud/core/backend_handle.py
januscloud/core/backend_server.py
januscloud/core/backend_session.py
januscloud/core/frontend_handle_base.py
januscloud/core/frontend_session.py
januscloud/core/plugin_base.py
januscloud/core/request.py
januscloud/proxy/__init__.py
januscloud/proxy/config.py
januscloud/proxy/main.py
januscloud/proxy/dao/__init__.py
januscloud/proxy/dao/mem_server_dao.py
januscloud/proxy/dao/mem_videocall_user_dao.py
januscloud/proxy/dao/rd_room_dao.py
januscloud/proxy/dao/rd_server_dao.py
januscloud/proxy/dao/rd_videocall_user_dao.py
januscloud/proxy/plugin/__init__.py
januscloud/proxy/plugin/dummytest.py
januscloud/proxy/plugin/echotest.py
januscloud/proxy/plugin/p2pcall.py
januscloud/proxy/plugin/videocall.py
januscloud/proxy/plugin/videoroom.py
januscloud/proxy/rest/__init__.py
janus_cloud-1.0.0.dist-info/LICENSE
janus_cloud-1.0.0.dist-info/METADATA
janus_cloud-1.0.0.dist-info/WHEEL
janus_cloud-1.0.0.dist-info/entry_points.txt
janus_cloud-1.0.0.dist-info/top_level.txt
janus_cloud-1.0.0.dist-info/RECORD
