Metadata-Version: 2.1
Name: janus-cloud
Version: 1.0.0
Summary: Janus-cloud is a cluster solution for Janus WebRTC server, by API proxy approach
Home-page: https://github.com/OpenSight/janus-cloud
Author: OpenSight
Author-email: public@opensight.cn
License: AGPLv3
Keywords: Janus cloud WebRTC
Platform: UNKNOWN
Classifier: Development Status :: 3 - Alpha
Classifier: Framework :: Pyramid
Classifier: Intended Audience :: System Administrators
Classifier: Intended Audience :: Developers
Classifier: Intended Audience :: Education
Classifier: Intended Audience :: Telecommunications Industry
Classifier: License :: OSI Approved :: GNU Affero General Public License v3
Classifier: Operating System :: POSIX :: Linux
Classifier: Programming Language :: Python
Classifier: Programming Language :: Python :: 3.5
Classifier: Programming Language :: Python :: 3.6
Classifier: Programming Language :: Python :: 3.7
Classifier: Programming Language :: Python :: 3.8
Classifier: Topic :: Communications :: Conferencing
Classifier: Topic :: Communications :: Internet Phone
Classifier: Topic :: Internet :: WWW/HTTP
License-File: LICENSE
Requires-Dist: gevent (==20.9.0)
Requires-Dist: ws4py (==0.5.1)
Requires-Dist: PyYAML (==5.4)
Requires-Dist: pyramid (==1.10.4)
Requires-Dist: requests (==2.20.0)
Requires-Dist: python-daemon (==2.2.3)
Requires-Dist: redis (==3.5.2)
